[
    {
        "title": "Branding",
        "img": "brands/Moon_News.jpg",
        "details": "brands/Moon_News_Style_Guides.pdf"
    },
    {
        "title": "Logo Design",
        "img": ""
    },
    {
        "title": "Stationary",
        "img": ""
    },
    {
        "title": "Social Media",
        "img": ""
    },
    {
        "title": "Apparel",
        "img": ""
    },
    {
        "title": "Website & app design",
        "img": ""
    },
    {
        "title": "Outdoor Graphics",
        "img": ""
    },
    {
        "title": "Logo & 2D Animation",
        "img": ""
    },
    {
        "title": "Twitch Packs",
        "img": ""
    },
    {
        "title": "Motion Graphics",
        "img": ""
    }
]